crooked_airflow_utils/__init__.py
crooked_airflow_utils/crooked_airflow_utils.py
crooked_airflow_utils-0.1.0.dist-info/LICENSE
crooked_airflow_utils-0.1.0.dist-info/METADATA
crooked_airflow_utils-0.1.0.dist-info/WHEEL
crooked_airflow_utils-0.1.0.dist-info/entry_points.txt
crooked_airflow_utils-0.1.0.dist-info/top_level.txt
crooked_airflow_utils-0.1.0.dist-info/RECORD
