Metadata-Version: 2.1
Name: crooked-airflow-utils
Version: 0.1.0
Summary: test
Home-page: https://jungssg.github.io/crooked_airflow_utils
Author: crooked
Author-email: younwjdtjr@naver.com
License: GNU General Public License (GPL)
Project-URL: Bug Tracker, https://github.com/jungssg/crooked_airflow_utils/issues
Platform: macOS
Classifier: Programming Language :: Python :: 3
Classifier: License :: OSI Approved :: GNU General Public License (GPL)
Classifier: Operating System :: OS Independent
Requires-Python: >=3.6
License-File: LICENSE
